iflow_mcp_leshchenko1979_fast_mcp_telegram-0.11.0.dist-info/licenses/LICENSE
src/__init__.py
src/_version.py
src/cli_setup.py
src/server.py
src/client/__init__.py
src/client/connection.py
src/config/__init__.py
src/config/logging.py
src/config/server_config.py
src/config/settings.py
src/server_components/__init__.py
src/server_components/auth.py
src/server_components/bot_restrictions.py
src/server_components/errors.py
src/server_components/health.py
src/server_components/mtproto_api.py
src/server_components/tools_register.py
src/server_components/web_setup.py
src/tools/__init__.py
src/tools/contacts.py
src/tools/links.py
src/tools/messages.py
src/tools/mtproto.py
src/tools/search.py
src/utils/__init__.py
src/utils/entity.py
src/utils/error_handling.py
src/utils/helpers.py
src/utils/logging_utils.py
src/utils/mcp_config.py
src/utils/message_format.py
iflow_mcp_leshchenko1979_fast_mcp_telegram-0.11.0.dist-info/METADATA
iflow_mcp_leshchenko1979_fast_mcp_telegram-0.11.0.dist-info/WHEEL
iflow_mcp_leshchenko1979_fast_mcp_telegram-0.11.0.dist-info/entry_points.txt
iflow_mcp_leshchenko1979_fast_mcp_telegram-0.11.0.dist-info/top_level.txt
iflow_mcp_leshchenko1979_fast_mcp_telegram-0.11.0.dist-info/RECORD
