Metadata-Version: 2.4
Name: iflow-mcp_leshchenko1979_fast-mcp-telegram
Version: 0.11.0
Summary: MCP server with Telegram search and messaging capabilities
Author-email: Alexey Leshchenko <leshchenko@gmail.com>
License-Expression: MIT
Project-URL: Homepage, https://github.com/leshchenko1979/fast-mcp-telegram
Project-URL: Repository, https://github.com/leshchenko1979/fast-mcp-telegram
Project-URL: Documentation, https://github.com/leshchenko1979/fast-mcp-telegram#readme
Project-URL: Issues, https://github.com/leshchenko1979/fast-mcp-telegram/issues
Classifier: Development Status :: 4 - Beta
Classifier: Intended Audience :: Developers
Classifier: Operating System :: OS Independent
Classifier: Programming Language :: Python :: 3
Classifier: Programming Language :: Python :: 3.11
Classifier: Programming Language :: Python :: 3.12
Classifier: Programming Language :: Python :: 3.13
Classifier: Programming Language :: Python :: 3.14
Classifier: Topic :: Communications :: Chat
Classifier: Topic :: Software Development :: Libraries :: Python Modules
Requires-Python: >=3.11
License-File: LICENSE
Requires-Dist: aiohttp
Requires-Dist: fastmcp
Requires-Dist: telethon
Requires-Dist: jinja2
Requires-Dist: pydantic-settings
Dynamic: license-file
